{"nodes":[{"id":"catalog_pg_auth_members","label":"pg_auth_members.h","file_type":"code","source_file":"E:\\Talent-Mesh\\services\\pgsql\\include\\server\\catalog\\pg_auth_members.h","source_location":"L1"}],"edges":[{"source":"catalog_pg_auth_members","target":"genbki","relation":"imports","confidence":"EXTRACTED","source_file":"E:\\Talent-Mesh\\services\\pgsql\\include\\server\\catalog\\pg_auth_members.h","source_location":"L22","weight":1},{"source":"catalog_pg_auth_members","target":"pg_auth_members_d","relation":"imports","confidence":"EXTRACTED","source_file":"E:\\Talent-Mesh\\services\\pgsql\\include\\server\\catalog\\pg_auth_members.h","source_location":"L23","weight":1}]}