{"nodes":[{"id":"guards_roles_guard","label":"roles.guard.ts","file_type":"code","source_file":"E:\\Talent-Mesh\\backend\\src\\common\\guards\\roles.guard.ts","source_location":"L1"},{"id":"guards_roles_guard_rolesguard","label":"RolesGuard","file_type":"code","source_file":"E:\\Talent-Mesh\\backend\\src\\common\\guards\\roles.guard.ts","source_location":"L20"},{"id":"guards_roles_guard_rolesguard_constructor","label":".constructor()","file_type":"code","source_file":"E:\\Talent-Mesh\\backend\\src\\common\\guards\\roles.guard.ts","source_location":"L21"},{"id":"guards_roles_guard_rolesguard_canactivate","label":".canActivate()","file_type":"code","source_file":"E:\\Talent-Mesh\\backend\\src\\common\\guards\\roles.guard.ts","source_location":"L23"}],"edges":[{"source":"guards_roles_guard","target":"common","relation":"imports_from","confidence":"EXTRACTED","source_file":"E:\\Talent-Mesh\\backend\\src\\common\\guards\\roles.guard.ts","source_location":"L1","weight":1},{"source":"guards_roles_guard","target":"core","relation":"imports_from","confidence":"EXTRACTED","source_file":"E:\\Talent-Mesh\\backend\\src\\common\\guards\\roles.guard.ts","source_location":"L7","weight":1},{"source":"guards_roles_guard","target":"client","relation":"imports_from","confidence":"EXTRACTED","source_file":"E:\\Talent-Mesh\\backend\\src\\common\\guards\\roles.guard.ts","source_location":"L8","weight":1},{"source":"guards_roles_guard","target":"e_talent_mesh_backend_src_common_decorators_roles_decorator","relation":"imports_from","confidence":"EXTRACTED","source_file":"E:\\Talent-Mesh\\backend\\src\\common\\guards\\roles.guard.ts","source_location":"L9","weight":1},{"source":"guards_roles_guard","target":"decorators_roles_roles_key","relation":"imports","confidence":"EXTRACTED","source_file":"E:\\Talent-Mesh\\backend\\src\\common\\guards\\roles.guard.ts","source_location":"L9","weight":1},{"source":"guards_roles_guard","target":"e_talent_mesh_backend_src_modules_auth_interfaces_jwt_payload_interface","relation":"imports_from","confidence":"EXTRACTED","source_file":"E:\\Talent-Mesh\\backend\\src\\common\\guards\\roles.guard.ts","source_location":"L10","weight":1},{"source":"guards_roles_guard","target":"interfaces_jwt_payload_jwtpayload","relation":"imports","confidence":"EXTRACTED","source_file":"E:\\Talent-Mesh\\backend\\src\\common\\guards\\roles.guard.ts","source_location":"L10","weight":1},{"source":"guards_roles_guard","target":"guards_roles_guard_rolesguard","relation":"contains","confidence":"EXTRACTED","source_file":"E:\\Talent-Mesh\\backend\\src\\common\\guards\\roles.guard.ts","source_location":"L20","weight":1},{"source":"guards_roles_guard_rolesguard","target":"guards_roles_guard_rolesguard_constructor","relation":"method","confidence":"EXTRACTED","source_file":"E:\\Talent-Mesh\\backend\\src\\common\\guards\\roles.guard.ts","source_location":"L21","weight":1},{"source":"guards_roles_guard_rolesguard","target":"guards_roles_guard_rolesguard_canactivate","relation":"method","confidence":"EXTRACTED","source_file":"E:\\Talent-Mesh\\backend\\src\\common\\guards\\roles.guard.ts","source_location":"L23","weight":1}]}