{"nodes":[{"id":"access_hio","label":"hio.h","file_type":"code","source_file":"E:\\Talent-Mesh\\services\\pgsql\\include\\server\\access\\hio.h","source_location":"L1"}],"edges":[{"source":"access_hio","target":"htup","relation":"imports","confidence":"EXTRACTED","source_file":"E:\\Talent-Mesh\\services\\pgsql\\include\\server\\access\\hio.h","source_location":"L17","weight":1},{"source":"access_hio","target":"buf","relation":"imports","confidence":"EXTRACTED","source_file":"E:\\Talent-Mesh\\services\\pgsql\\include\\server\\access\\hio.h","source_location":"L18","weight":1},{"source":"access_hio","target":"relcache","relation":"imports","confidence":"EXTRACTED","source_file":"E:\\Talent-Mesh\\services\\pgsql\\include\\server\\access\\hio.h","source_location":"L19","weight":1}]}