{"nodes":[{"id":"reviews_reviews_controller","label":"reviews.controller.ts","file_type":"code","source_file":"E:\\Talent-Mesh\\backend\\src\\modules\\reviews\\reviews.controller.ts","source_location":"L1"},{"id":"reviews_reviews_controller_reviewscontroller","label":"ReviewsController","file_type":"code","source_file":"E:\\Talent-Mesh\\backend\\src\\modules\\reviews\\reviews.controller.ts","source_location":"L12"},{"id":"reviews_reviews_controller_reviewscontroller_constructor","label":".constructor()","file_type":"code","source_file":"E:\\Talent-Mesh\\backend\\src\\modules\\reviews\\reviews.controller.ts","source_location":"L13"},{"id":"reviews_reviews_controller_reviewscontroller_createreview","label":".createReview()","file_type":"code","source_file":"E:\\Talent-Mesh\\backend\\src\\modules\\reviews\\reviews.controller.ts","source_location":"L17"},{"id":"reviews_reviews_controller_reviewscontroller_getstudentreviews","label":".getStudentReviews()","file_type":"code","source_file":"E:\\Talent-Mesh\\backend\\src\\modules\\reviews\\reviews.controller.ts","source_location":"L28"}],"edges":[{"source":"reviews_reviews_controller","target":"common","relation":"imports_from","confidence":"EXTRACTED","source_file":"E:\\Talent-Mesh\\backend\\src\\modules\\reviews\\reviews.controller.ts","source_location":"L1","weight":1},{"source":"reviews_reviews_controller","target":"swagger","relation":"imports_from","confidence":"EXTRACTED","source_file":"E:\\Talent-Mesh\\backend\\src\\modules\\reviews\\reviews.controller.ts","source_location":"L2","weight":1},{"source":"reviews_reviews_controller","target":"e_talent_mesh_backend_src_modules_reviews_reviews_service","relation":"imports_from","confidence":"EXTRACTED","source_file":"E:\\Talent-Mesh\\backend\\src\\modules\\reviews\\reviews.controller.ts","source_location":"L3","weight":1},{"source":"reviews_reviews_controller","target":"reviews_reviews_reviewsservice","relation":"imports","confidence":"EXTRACTED","source_file":"E:\\Talent-Mesh\\backend\\src\\modules\\reviews\\reviews.controller.ts","source_location":"L3","weight":1},{"source":"reviews_reviews_controller","target":"e_talent_mesh_backend_src_modules_reviews_dto_review_dto","relation":"imports_from","confidence":"EXTRACTED","source_file":"E:\\Talent-Mesh\\backend\\src\\modules\\reviews\\reviews.controller.ts","source_location":"L4","weight":1},{"source":"reviews_reviews_controller","target":"dto_review_createreviewdto","relation":"imports","confidence":"EXTRACTED","source_file":"E:\\Talent-Mesh\\backend\\src\\modules\\reviews\\reviews.controller.ts","source_location":"L4","weight":1},{"source":"reviews_reviews_controller","target":"e_talent_mesh_backend_src_common_decorators_current_user_decorator","relation":"imports_from","confidence":"EXTRACTED","source_file":"E:\\Talent-Mesh\\backend\\src\\modules\\reviews\\reviews.controller.ts","source_location":"L5","weight":1},{"source":"reviews_reviews_controller","target":"decorators_current_user_currentuser","relation":"imports","confidence":"EXTRACTED","source_file":"E:\\Talent-Mesh\\backend\\src\\modules\\reviews\\reviews.controller.ts","source_location":"L5","weight":1},{"source":"reviews_reviews_controller","target":"e_talent_mesh_backend_src_modules_auth_interfaces_jwt_payload_interface","relation":"imports_from","confidence":"EXTRACTED","source_file":"E:\\Talent-Mesh\\backend\\src\\modules\\reviews\\reviews.controller.ts","source_location":"L6","weight":1},{"source":"reviews_reviews_controller","target":"interfaces_jwt_payload_jwtpayload","relation":"imports","confidence":"EXTRACTED","source_file":"E:\\Talent-Mesh\\backend\\src\\modules\\reviews\\reviews.controller.ts","source_location":"L6","weight":1},{"source":"reviews_reviews_controller","target":"e_talent_mesh_backend_src_common_decorators_public_decorator","relation":"imports_from","confidence":"EXTRACTED","source_file":"E:\\Talent-Mesh\\backend\\src\\modules\\reviews\\reviews.controller.ts","source_location":"L7","weight":1},{"source":"reviews_reviews_controller","target":"decorators_public_public","relation":"imports","confidence":"EXTRACTED","source_file":"E:\\Talent-Mesh\\backend\\src\\modules\\reviews\\reviews.controller.ts","source_location":"L7","weight":1},{"source":"reviews_reviews_controller","target":"reviews_reviews_controller_reviewscontroller","relation":"contains","confidence":"EXTRACTED","source_file":"E:\\Talent-Mesh\\backend\\src\\modules\\reviews\\reviews.controller.ts","source_location":"L12","weight":1},{"source":"reviews_reviews_controller_reviewscontroller","target":"reviews_reviews_controller_reviewscontroller_constructor","relation":"method","confidence":"EXTRACTED","source_file":"E:\\Talent-Mesh\\backend\\src\\modules\\reviews\\reviews.controller.ts","source_location":"L13","weight":1},{"source":"reviews_reviews_controller_reviewscontroller","target":"reviews_reviews_controller_reviewscontroller_createreview","relation":"method","confidence":"EXTRACTED","source_file":"E:\\Talent-Mesh\\backend\\src\\modules\\reviews\\reviews.controller.ts","source_location":"L17","weight":1},{"source":"reviews_reviews_controller_reviewscontroller","target":"reviews_reviews_controller_reviewscontroller_getstudentreviews","relation":"method","confidence":"EXTRACTED","source_file":"E:\\Talent-Mesh\\backend\\src\\modules\\reviews\\reviews.controller.ts","source_location":"L28","weight":1}]}